Workbook
Name CATEGORÍA: Febrero!#REF!

Sheet Resumen anual
B2: RESUMEN ANUAL | P2: Objetivo de ahorro mensual | Q2: 350
C4: ENERO | D4: FEBRERO | E4: MARZO | F4: ABRIL | G4: MAYO | H4: JUNIO | I4: JULIO | J4: AGOSTO | K4: SEPTIEMBRE | L4: OCTUBRE | M4: NOVIEMBRE | N4: DICIEMBRE
B5: Ingresos | C5: =Enero!$D$2 -> 2271 | D5: =Febrero!$D$2 -> 2077 | E5: =Marzo!$D$2 -> 2010 | F5: =Abril!$D$2 -> 2275 | G5: =Mayo!$D$2 -> 1850 | H5: =Junio!$D$2 -> 2147 | I5: =Julio!$D$2 -> 2550 | J5: =Agosto!$D$2 -> 2095 | K5: =Septiembre!$D$2 -> 1625 | L5: =Octubre!$D$2 -> 1973 | M5: =Noviembre!$D$2 -> 2130 | N5: =Diciembre!$D$2 -> 1829
B6: Gastos | C6: =Enero!$I$2 -> 1915 | D6: =Febrero!$I$2 -> 1943 | E6: =Marzo!$I$2 -> 1754 | F6: =Abril!$I$2 -> 2505 | G6: =Mayo!$I$2 -> 1740 | H6: =Junio!$I$2 -> 1915 | I6: =Julio!$I$2 -> 1925 | J6: =Agosto!$I$2 -> 1805 | K6: =Septiembre!$I$2 -> 1715 | L6: =Octubre!$I$2 -> 1810 | M6: =Noviembre!$I$2 -> 1893 | N6: =Diciembre!$I$2 -> 1718
B8: Resultado | C8: =C5-C6 -> 356 | D8: =D5-D6 -> 134 | E8: =E5-E6 -> 256 | F8: =F5-F6 -> -230 | G8: =G5-G6 -> 110 | H8: =H5-H6 -> 232 | I8: =I5-I6 -> 625 | J8: =J5-J6 -> 290 | ... N8: =N5-N6 -> 111
B9: TOTAL | C9: =SUM(C8) -> 356 | D9: =SUM(C9+D8) -> 490 | E9: =SUM(D9+E8) -> 746 | F9: =SUM(E9+F8) -> 516 | G9: =SUM(F9+G8) -> 626 | H9: =SUM(G9+H8) -> 858 | I9: =SUM(H9+I8) -> 1483 | J9: =SUM(I9+J8) -> 1773 | K9: =SUM(J9+K8) -> 1683 | ... N9: =SUM(M9+N8) -> 2194
B28: Media de ingresos | E28: Media de gastos | I28: Mayor ingreso | J28: Menor ingreso | M28: Mayor gasto | N28: Menor gasto
B29: =AVERAGEIF(C5:N5,"<>0") -> 2069.3333 | E29: =AVERAGEIF(C6:N6,"<>0") -> 1886.5 | I29: =MAX(C5:N5) -> 2550 | J29: =_xlfn.MINIFS(C5:N5,C5:N5,"<>0") -> 1625 | M29: =MAX(C6:N6) -> 2505 | N29: =_xlfn.MINIFS(C6:N6,C6:N6,"<>0") -> 1715

Sheet Enero
B2: Ingresos enero | C2: Total | D2: =SUM(ingresos_enero[Monto]) -> 2271 | G2: Gastos enero | H2: Total | I2: =GETPIVOTDATA("Monto",$L$4) -> 1915 | L2: Gastos por categoría
B4: Concepto | C4: Categoría | D4: Monto | G4: Concepto | H4: Categoría | I4: Monto | L4: CATEGORÍA | M4: Suma
B5: Trabajo 1 | C5: Trabajo | D5: 1675 | G5: Gasolina | H5: Transporte | I5: 300 | L5: Transporte | M5: 300
B6: Paga extra Navidad | C6: Extra | D6: 200 | G6: Hipoteca | H6: Casa | I6: 650 | L6: Ropa | M6: 150
B7: Bolsa | C7: Inversiones | D7: 349 | G7: Cena amigos | H7: Ocio | I7: 45 | L7: Ocio | M7: 170
B8: Intereses y dividendos | C8: Inversiones | D8: 47 | G8: Comida del mes | H8: Comida | I8: 300 | L8: Deporte | M8: 145
G9: Entrenamientos tenis | H9: Deporte | I9: 120 | L9: Comida | M9: 300
G10: Gimnasio | H10: Deporte | I10: 25 | L10: Casa | M10: 850
G11: Luz y teléfono | H11: Casa | I11: 200 | L11: TOTAL | M11: 1915
G12: Cervezas y juegos | H12: Ocio | I12: 125
G13: Ropa trabajo | H13: Ropa | I13: 150

Sheet Febrero
B2: Ingresos febrero | C2: Total | D2: =SUM(ingresos_febrero[Monto]) -> 2077 | G2: Gastos febrero | H2: Total | I2: =GETPIVOTDATA("Monto",$L$4) -> 1943 | L2: Gastos por categoría
B4: Concepto | C4: Categoría | D4: Monto | G4: Concepto | H4: Categoría | I4: Monto | L4: CATEGORÍA | M4: Total
B5: Trabajo 1 | C5: Trabajo | D5: 1675 | G5: Gasolina | H5: Transporte | I5: 250 | L5: Transporte | M5: 250
B6: Bolsa | C6: Inversiones | D6: 367 | G6: Hipoteca | H6: Casa | I6: 650 | L6: Ropa | M6: 120
B7: Intereses y dividendos | C7: Inversiones | D7: 35 | G7: Cena amigos | H7: Ocio | I7: 68 | L7: Ocio | M7: 208
G8: Comida del mes | H8: Comida | I8: 350 | L8: Deporte | M8: 145
G9: Entrenamientos tenis | H9: Deporte | I9: 120 | L9: Comida | M9: 350
G10: Gimnasio | H10: Deporte | I10: 25 | L10: Casa | M10: 870
G11: Luz y teléfono | H11: Casa | I11: 220 | L11: TOTAL | M11: 1943
G12: Cervezas y juegos | H12: Ocio | I12: 140
G13: Ropa trabajo | H13: Ropa | I13: 25

Sheet Marzo
B2: Ingresos marzo | C2: Total | D2: =SUM(ingresos_marzo[Monto]) -> 2010 | G2: Gastos marzo | H2: Total | I2: =GETPIVOTDATA("Monto",$L$4) -> 1754 | L2: Gastos por categoría
B4: Concepto | C4: Categoría | D4: Monto | G4: Concepto | H4: Categoría | I4: Monto | L4: CATEGORÍA | M4: Total
B5: Trabajo 1 | C5: Trabajo | D5: 1675 | G5: Gasolina | H5: Transporte | I5: 200 | L5: Transporte | M5: 200
B6: Bolsa | C6: Inversiones | D6: 300 | G6: Hipoteca | H6: Casa | I6: 650 | L6: Ocio | M6: 230
B7: Intereses y dividendos | C7: Inversiones | D7: 35 | G7: Cena amigos | H7: Ocio | I7: 80 | L7: Deporte | M7: 145
G8: Comida del mes | H8: Comida | I8: 340 | L8: Comida | M8: 340
G9: Entrenamientos tenis | H9: Deporte | I9: 120 | L9: Casa | M9: 839
G10: Gimnasio | H10: Deporte | I10: 25 | L10: TOTAL | M10: 1754
G11: Luz y teléfono | H11: Casa | I11: 189
G12: Cervezas y juegos | H12: Ocio | I12: 150

Sheet Abril
B2: Ingresos abril | C2: Total | D2: =SUM(ingresos_abril[Monto]) -> 2275 | G2: Gastos abril | H2: Total | I2: =GETPIVOTDATA("Monto",$L$4) -> 2505 | L2: Gastos por categoría
B4: Concepto | C4: Categoría | D4: Monto | G4: Concepto | H4: Categoría | I4: Monto | L4: CATEGORÍA | M4: Total
B5: Trabajo 1 | C5: Trabajo | D5: 1675 | G5: Gasolina | H5: Transporte | I5: 320 | L5: Transporte | M5: 900
B6: Bolsa | C6: Inversiones | D6: 550 | G6: Hipoteca | H6: Casa | I6: 650 | L6: Ropa | M6: 150
B7: Intereses y dividendos | C7: Inversiones | D7: 50 | G7: Cena amigos | H7: Ocio | I7: 80 | L7: Ocio | M7: 180
G8: Comida del mes | H8: Comida | I8: 280 | L8: Deporte | M8: 145
G9: Entrenamientos tenis | H9: Deporte | I9: 120 | L9: Comida | M9: 280
G10: Gimnasio | H10: Deporte | I10: 25 | L10: Casa | M10: 850
G11: Luz y teléfono | H11: Casa | I11: 200 | L11: TOTAL | M11: 2505
G12: Cervezas y juegos | H12: Ocio | I12: 100
G13: Ropa trabajo | H13: Ropa | I13: 150
G14: Seguro coche | H14: Transporte | I14: 580

Sheet Mayo
B2: Ingresos mayo | C2: Total | D2: =SUM(ingresos_mayo[Monto]) -> 1850 | G2: Gastos mayo | H2: Total | I2: =GETPIVOTDATA("Monto",$L$4) -> 1740 | L2: Gastos por categoría
B4: Concepto | C4: Categoría | D4: Monto | G4: Concepto | H4: Categoría | I4: Monto | L4: CATEGORÍA | M4: Total
B5: Trabajo 1 | C5: Trabajo | D5: 1675 | G5: Gasolina | H5: Transporte | I5: 320 | L5: Transporte | M5: 320
B6: Bolsa | C6: Inversiones | D6: 150 | G6: Hipoteca | H6: Casa | I6: 650 | L6: Ocio | M6: 125
B7: Intereses y dividendos | C7: Inversiones | D7: 25 | G7: Cena amigos | H7: Ocio | I7: 45 | L7: Deporte | M7: 145
G8: Comida del mes | H8: Comida | I8: 300 | L8: Comida | M8: 300
G9: Entrenamientos tenis | H9: Deporte | I9: 120 | L9: Casa | M9: 850
G10: Gimnasio | H10: Deporte | I10: 25 | L10: TOTAL | M10: 1740
G11: Luz y teléfono | H11: Casa | I11: 200
G12: Cervezas y juegos | H12: Ocio | I12: 80

Sheet Junio
B2: Ingresos junio | C2: Total | D2: =SUM(ingresos_junio[Monto]) -> 2147 | G2: Gastos junio | H2: Total | I2: =GETPIVOTDATA("Monto",$L$4) -> 1915 | L2: Gastos por categoría
B4: Concepto | C4: Categoría | D4: Monto | G4: Concepto | H4: Categoría | I4: Monto | L4: CATEGORÍA | M4: Total
B5: Trabajo 1 | C5: Trabajo | D5: 1675 | G5: Gasolina | H5: Transporte | I5: 350 | L5: Transporte | M5: 350
B6: Bolsa | C6: Inversiones | D6: 440 | G6: Hipoteca | H6: Casa | I6: 650 | L6: Ropa | M6: 50
B7: Intereses y dividendos | C7: Inversiones | D7: 32 | G7: Cena amigos | H7: Ocio | I7: 60 | L7: Ocio | M7: 200
G8: Comida del mes | H8: Comida | I8: 340 | L8: Deporte | M8: 145
G9: Entrenamientos tenis | H9: Deporte | I9: 120 | L9: Comida | M9: 340
G10: Gimnasio | H10: Deporte | I10: 25 | L10: Casa | M10: 830
G11: Luz y teléfono | H11: Casa | I11: 180 | L11: TOTAL | M11: 1915
G12: Cervezas y juegos | H12: Ocio | I12: 140
G13: Ropa trabajo | H13: Ropa | I13: 50

Sheet Julio
B2: Ingresos julio | C2: Total | D2: =SUM(ingresos_julio[Monto]) -> 2550 | G2: Gastos julio | H2: Total | I2: =GETPIVOTDATA("Monto",$L$4) -> 1925 | L2: Gastos por categoría
B4: Concepto | C4: Categoría | D4: Monto | G4: Concepto | H4: Categoría | I4: Monto | L4: CATEGORÍA | M4: Total
B5: Trabajo 1 | C5: Trabajo | D5: 1675 | G5: Gasolina | H5: Transporte | I5: 320 | L5: Transporte | M5: 320
B6: Paga extra Verano | C6: Extra | D6: 600 | G6: Hipoteca | H6: Casa | I6: 650 | L6: Ocio | M6: 250
B7: Bolsa | C7: Inversiones | D7: 240 | G7: Cena amigos | H7: Ocio | I7: 50 | L7: Deporte | M7: 145
B8: Intereses y dividendos | C8: Inversiones | D8: 35 | G8: Comida del mes | H8: Comida | I8: 340 | L8: Comida | M8: 340
G9: Entrenamientos tenis | H9: Deporte | I9: 120 | L9: Casa | M9: 870
G10: Gimnasio | H10: Deporte | I10: 25 | L10: TOTAL | M10: 1925
G11: Luz y teléfono | H11: Casa | I11: 220
G12: Cervezas y juegos | H12: Ocio | I12: 200

Sheet Agosto
B2: Ingresos agosto | C2: Total | D2: =SUM(ingresos_agosto[Monto]) -> 2095 | G2: Gastos agosto | H2: Total | I2: =GETPIVOTDATA("Monto",$L$4) -> 1805 | L2: Gastos por categoría
B4: Concepto | C4: Categoría | D4: Monto | G4: Concepto | H4: Categoría | I4: Monto | L4: CATEGORÍA | M4: Total
B5: Trabajo 1 | C5: Trabajo | D5: 1675 | G5: Gasolina | H5: Transporte | I5: 280 | L5: Transporte | M5: 280
B6: Bolsa | C6: Inversiones | D6: 400 | G6: Hipoteca | H6: Casa | I6: 650 | L6: Ocio | M6: 180
B7: Intereses y dividendos | C7: Inversiones | D7: 20 | G7: Cena amigos | H7: Ocio | I7: 60 | L7: Deporte | M7: 145
G8: Comida del mes | H8: Comida | I8: 300 | L8: Comida | M8: 300
G9: Entrenamientos tenis | H9: Deporte | I9: 120 | L9: Casa | M9: 900
G10: Gimnasio | H10: Deporte | I10: 25 | L10: TOTAL | M10: 1805
G11: Luz y teléfono | H11: Casa | I11: 250
G12: Cervezas y juegos | H12: Ocio | I12: 120

Sheet Septiembre
B2: Ingresos septiembre | C2: Total | D2: =SUM(ingresos_septiembre[Monto]) -> 1625 | G2: Gastos septiembre | H2: Total | I2: =GETPIVOTDATA("Monto",$L$4) -> 1715 | L2: Gastos por categoría
B4: Concepto | C4: Categoría | D4: Monto | G4: Concepto | H4: Categoría | I4: Monto | L4: CATEGORÍA | M4: Total
B5: Trabajo 1 | C5: Trabajo | D5: 1675 | G5: Gasolina | H5: Transporte | I5: 260 | L5: Transporte | M5: 260
B6: Bolsa | C6: Inversiones | D6: -100 | G6: Hipoteca | H6: Casa | I6: 650 | L6: Ocio | M6: 170
B7: Intereses y dividendos | C7: Inversiones | D7: 50 | G7: Cena amigos | H7: Ocio | I7: 45 | L7: Deporte | M7: 145
G8: Comida del mes | H8: Comida | I8: 290 | L8: Comida | M8: 290
G9: Entrenamientos tenis | H9: Deporte | I9: 120 | L9: Casa | M9: 850
G10: Gimnasio | H10: Deporte | I10: 25 | L10: TOTAL | M10: 1715
G11: Luz y teléfono | H11: Casa | I11: 200
G12: Cervezas y juegos | H12: Ocio | I12: 125

Sheet Octubre
B2: Ingresos octubre | C2: Total | D2: =SUM(ingresos_octubre[Monto]) -> 1973 | G2: Gastos octubre | H2: Total | I2: =GETPIVOTDATA("Monto",$L$4) -> 1810 | L2: Gastos por categoría
B4: Concepto | C4: Categoría | D4: Monto | G4: Concepto | H4: Categoría | I4: Monto | L4: CATEGORÍA | M4: Total
B5: Trabajo 1 | C5: Trabajo | D5: 1675 | G5: Gasolina | H5: Transporte | I5: 320 | L5: Transporte | M5: 320
B6: Bolsa | C6: Inversiones | D6: 260 | G6: Hipoteca | H6: Casa | I6: 650 | L6: Ocio | M6: 175
B7: Intereses y dividendos | C7: Inversiones | D7: 38 | G7: Cena amigos | H7: Ocio | I7: 50 | L7: Deporte | M7: 145
G8: Comida del mes | H8: Comida | I8: 320 | L8: Comida | M8: 320
G9: Entrenamientos tenis | H9: Deporte | I9: 120 | L9: Casa | M9: 850
G10: Gimnasio | H10: Deporte | I10: 25 | L10: TOTAL | M10: 1810
G11: Luz y teléfono | H11: Casa | I11: 200
G12: Cervezas y juegos | H12: Ocio | I12: 125

Sheet Noviembre
B2: Ingresos noviembre | C2: Total | D2: =SUM(ingresos_noviembre[Monto]) -> 2130 | G2: Gastos noviembre | H2: Total | I2: =GETPIVOTDATA("Monto",$L$4) -> 1893 | L2: Gastos por categoría
B4: Concepto | C4: Categoría | D4: Monto | G4: Concepto | H4: Categoría | I4: Monto | L4: CATEGORÍA | M4: Total
B5: Trabajo 1 | C5: Trabajo | D5: 1675 | G5: Gasolina | H5: Transporte | I5: 340 | L5: Transporte | M5: 340
B6: Bolsa | C6: Inversiones | D6: 400 | G6: Hipoteca | H6: Casa | I6: 650 | L6: Ropa | M6: 25
B7: Intereses y dividendos | C7: Inversiones | D7: 55 | G7: Cena amigos | H7: Ocio | I7: 80 | L7: Ocio | M7: 193
G8: Comida del mes | H8: Comida | I8: 320 | L8: Deporte | M8: 145
G9: Entrenamientos tenis | H9: Deporte | I9: 120 | L9: Comida | M9: 320
G10: Gimnasio | H10: Deporte | I10: 25 | L10: Casa | M10: 870
G11: Luz y teléfono | H11: Casa | I11: 220 | L11: TOTAL | M11: 1893
G12: Cervezas y juegos | H12: Ocio | I12: 113
G13: Ropa trabajo | H13: Ropa | I13: 25

Sheet Diciembre
B2: Ingresos diciembre | C2: Total | D2: =SUM(ingresos_diciembre[Monto]) -> 1829 | G2: Gastos diciembre | H2: Total | I2: =GETPIVOTDATA("Monto",$L$4) -> 1718 | L2: Gastos por categoría
B4: Concepto | C4: Categoría | D4: Monto | G4: Concepto | H4: Categoría | I4: Monto | L4: CATEGORÍA | M4: Total
B5: Trabajo 1 | C5: Trabajo | D5: 1675 | G5: Gasolina | H5: Transporte | I5: 260 | L5: Transporte | M5: 260
B6: Bolsa | C6: Inversiones | D6: 120 | G6: Hipoteca | H6: Casa | I6: 650 | L6: Ocio | M6: 135
B7: Intereses y dividendos | C7: Inversiones | D7: 34 | G7: Cena amigos | H7: Ocio | I7: 35 | L7: Deporte | M7: 145
G8: Comida del mes | H8: Comida | I8: 340 | L8: Comida | M8: 340
G9: Entrenamientos tenis | H9: Deporte | I9: 120 | L9: Casa | M9: 838
G10: Gimnasio | H10: Deporte | I10: 25 | L10: TOTAL | M10: 1718
G11: Luz y teléfono | H11: Casa | I11: 188
G12: Cervezas y juegos | H12: Ocio | I12: 100
